pybreach/__init__.py
pybreach/breachplot.py
pybreach/pybreach.py
pybreach-0.3.0.dist-info/DESCRIPTION.rst
pybreach-0.3.0.dist-info/METADATA
pybreach-0.3.0.dist-info/RECORD
pybreach-0.3.0.dist-info/WHEEL
pybreach-0.3.0.dist-info/metadata.json
pybreach-0.3.0.dist-info/top_level.txt
