Metadata-Version: 2.0
Name: pybreach
Version: 0.3.0
Summary: Identification of temporal consistency in rating curve data: Bidirectional Reach (BReach)
Home-page: https://github.com/stijnvanhoey/pybreach
Author: Stijn Van Hoey
Author-email: stijnvanhoey@gmail.com
License: MIT license
Keywords: pybreach
Platform: UNKNOWN
Classifier: Development Status :: 2 - Pre-Alpha
Classifier: Intended Audience :: Developers
Classifier: License :: OSI Approved :: MIT License
Classifier: Natural Language :: English
Classifier: Programming Language :: Python :: 2
Classifier: Programming Language :: Python :: 2.7
Classifier: Programming Language :: Python :: 3
Classifier: Programming Language :: Python :: 3.4
Classifier: Programming Language :: Python :: 3.5
Requires-Dist: numpy
